<?xml version="1.0" encoding="Shift_JIS"?>
<?xml-stylesheet type="text/xsl" href="hoot.xsl"?>
<!DOCTYPE gamelist [
	<!ELEMENT gamelist (game|bind|childlists)*>
	<!ATTLIST gamelist date CDATA #IMPLIED>
	<!ELEMENT childlists (list)*>
	<!ELEMENT list (#PCDATA)>
	<!ELEMENT bind (exts,driver,options?)>
	<!ELEMENT exts (ext)*>
	<!ELEMENT ext (#PCDATA)>
	<!ELEMENT game (name,driver,driveralias?,options?,romlist?,titlelist?)>
	<!ELEMENT name (#PCDATA)>
	<!ELEMENT driver (#PCDATA)>
	<!ATTLIST driver type CDATA #IMPLIED>
	<!ELEMENT driveralias (#PCDATA)>
	<!ATTLIST driveralias type CDATA #IMPLIED>
	<!ELEMENT options (option)*>
	<!ELEMENT option EMPTY>
	<!ATTLIST option name CDATA #REQUIRED
					 value CDATA #REQUIRED>
	<!ELEMENT romlist (rom)*>
	<!ATTLIST romlist archive CDATA #IMPLIED>
	<!ELEMENT rom (#PCDATA)>
	<!ATTLIST rom type CDATA #REQUIRED
				  offset CDATA #IMPLIED
				  crc32 CDATA #IMPLIED>
	<!ELEMENT titlelist (title|range)*>
	<!ELEMENT title (#PCDATA)>
	<!ATTLIST title code CDATA #REQUIRED
					type CDATA #IMPLIED>
	<!ELEMENT range (#PCDATA)>
	<!ATTLIST range min CDATA #REQUIRED
					max CDATA #REQUIRED
					extcode CDATA #IMPLIED>
]>
<gamelist date="2005/09/25">
	<!-- //Striker -->
	<game>
		<name>[PC-8801] メフィスト(OPNA)</name>
		<driver type="opna">pc88</driver>
		<driveralias type="NEC PC-8801">Striker</driveralias>
		<options>
			<option name="mdata_addr" value="0x9a00"/>
			<option name="use_vrtc" value="0x01"/>
		</options>
		<romlist archive="mephist">
			<rom type="code" offset="0x0000">PATCH</rom>
			<rom type="code" offset="0x8810">DRIVER.BIN</rom>
			<rom type="bgm" offset="0x00">MDAT1</rom>
			<rom type="bgm" offset="0x01">MDAT2</rom>
			<rom type="bgm" offset="0x02">MDAT3</rom>
			<rom type="bgm" offset="0x03">MDAT4</rom>
			<rom type="bgm" offset="0x04">MDAT5</rom>
			<rom type="bgm" offset="0x05">MDAT6</rom>
			<rom type="bgm" offset="0x06">MDAT7</rom>
			<rom type="bgm" offset="0x07">MDAT8</rom>
			<rom type="bgm" offset="0x08">MDAT9</rom>
			<rom type="bgm" offset="0x09">MDAT10</rom>
			<rom type="bgm" offset="0x10">MDAT11</rom>
			<rom type="bgm" offset="0x11">MDAT12</rom>
			<rom type="bgm" offset="0x12">MDAT13</rom>
			<rom type="bgm" offset="0x13">MDAT14</rom>
			<rom type="bgm" offset="0x14">MDAT15</rom>
		</romlist>
		<titlelist>
			<title code="0x00">オープニング</title>
			<title code="0x01">主人公のテーマ</title>
			<title code="0x02">カインのテーマ</title>
			<title code="0x03">所長のテーマ</title>
			<title code="0x04">調査のテーマ</title>
			<title code="0x05">恐怖のテーマ</title>
			<title code="0x06">メアリーのテーマ</title>
			<title code="0x07">アメリカ軍のテーマ</title>
			<title code="0x08">???</title>
			<title code="0x09">疑惑のテーマ</title>
			<title code="0x10">ニールセンのテーマ</title>
			<title code="0x11">レクイエムのテーマ</title>
			<title code="0x12">アーレスのテーマ</title>
			<title code="0x13">決戦のテーマ</title>
			<title code="0x14">エンディング?</title>
		</titlelist>
	</game>
	<game>
		<name>[PC-8801] メフィスト(OPN)</name>
		<driver type="opn">pc88</driver>
		<driveralias type="NEC PC-8801">Striker</driveralias>
		<options>
			<option name="mdata_addr" value="0x9a00"/>
			<option name="use_vrtc" value="0x01"/>
		</options>
		<romlist archive="mephist">
			<rom type="code" offset="0x0000">PATCH2</rom>
			<rom type="code" offset="0x8810">DRIVER.BIN</rom>
			<rom type="bgm" offset="0x00">MDAT1</rom>
			<rom type="bgm" offset="0x01">MDAT2</rom>
			<rom type="bgm" offset="0x02">MDAT3</rom>
			<rom type="bgm" offset="0x03">MDAT4</rom>
			<rom type="bgm" offset="0x04">MDAT5</rom>
			<rom type="bgm" offset="0x05">MDAT6</rom>
			<rom type="bgm" offset="0x06">MDAT7</rom>
			<rom type="bgm" offset="0x07">MDAT8</rom>
			<rom type="bgm" offset="0x08">MDAT9</rom>
			<rom type="bgm" offset="0x09">MDAT10</rom>
			<rom type="bgm" offset="0x10">MDAT11</rom>
			<rom type="bgm" offset="0x11">MDAT12</rom>
			<rom type="bgm" offset="0x12">MDAT13</rom>
			<rom type="bgm" offset="0x13">MDAT14</rom>
			<rom type="bgm" offset="0x14">MDAT15</rom>
		</romlist>
		<titlelist>
			<title code="0x00">オープニング</title>
			<title code="0x01">主人公のテーマ</title>
			<title code="0x02">カインのテーマ</title>
			<title code="0x03">所長のテーマ</title>
			<title code="0x04">調査のテーマ</title>
			<title code="0x05">恐怖のテーマ</title>
			<title code="0x06">メアリーのテーマ</title>
			<title code="0x07">アメリカ軍のテーマ</title>
			<title code="0x08">???</title>
			<title code="0x09">疑惑のテーマ</title>
			<title code="0x10">ニールセンのテーマ</title>
			<title code="0x11">レクイエムのテーマ</title>
			<title code="0x12">アーレスのテーマ</title>
			<title code="0x13">決戦のテーマ</title>
			<title code="0x14">エンディング?</title>
		</titlelist>
	</game>
	<game>
		<name>[X68000] 学園都市Z</name>
		<driver type="generic">x68k</driver>
		<driveralias type="SHARP X68000">Striker</driveralias>
		<options>
			<option name="mfp"     value="1"/>
			<option name="dmaint"  value="1"/>
		</options>
		<romlist archive="gktz68snd">
			<rom type="code" offset="0x000000">gktz68snd.bin</rom>
			<rom type="x"    offset="0x010000">tenq.x</rom>
			<rom type="code" offset="0x01a000">tone.odq</rom>
			<rom type="code" offset="0x020000">BGMSONGS.DAT</rom>
			<rom type="code" offset="0x030000">adpcm.dat</rom>
		</romlist>
		<titlelist>
			<range min="0x02" max="0x0f" extcode="1">BGM %02x</range>
		</titlelist>
	</game>
</gamelist>
